[{"Tipo":"CCA","Bloque":"Risk Management","Subbloque":"Risk Management","Definición":"Comments","Valor":null},{"Tipo":"CCA","Bloque":"Strategy","Subbloque":"Strategy","Definición":"How is the client’s portfolio of products and services shifting towards climate-aligned activities?","Valor":null},{"Tipo":"CCA","Bloque":"Strategy","Subbloque":"Carbon pricing","Definición":"Internal CO2 price","Valor":null},{"Tipo":"CCA","Bloque":"Strategy","Subbloque":"Net Zero","Definición":"Does the company have a Net Zero Target","Valor":null},{"Tipo":"CCA","Bloque":"Strategy","Subbloque":"Net Zero","Definición":"If yes please specify Net Zero target year","Valor":null}]